.gitignore
AUTHORS
CHANGES
LICENSE
MANIFEST.in
Makefile
README.rst
setup.cfg
setup.py
docs/Makefile
docs/api.rst
docs/conf.py
docs/firstapp.rst
docs/index.rst
docs/installation.rst
docs/introduction.rst
examples/available.py
examples/locate.py
examples/sample_sprintkit.conf
examples/sms.py
src/sprintkit/__init__.py
src/sprintkit/errors.py
src/sprintkit/gps.py
src/sprintkit/services.py
src/sprintkit.egg-info/PKG-INFO
src/sprintkit.egg-info/SOURCES.txt
src/sprintkit.egg-info/dependency_links.txt
src/sprintkit.egg-info/not-zip-safe
src/sprintkit.egg-info/requires.txt
src/sprintkit.egg-info/top_level.txt
tests/__init__.py
tests/functional/__init__.py
tests/functional/fixtures.py
tests/functional/sample_params.py
tests/functional/sample_sprintkit.conf
tests/functional/test_account.py
tests/functional/test_geofence.py
tests/functional/test_location.py
tests/functional/test_perimeter.py
tests/functional/test_presence.py
tests/functional/test_sms.py