Metadata-Version: 1.0
Name: sprintkit
Version: 0.1.0
Summary: Access Sprint's Network APIs Through Python
Home-page: https://github.com/ericem/sprintkit
Author: Eric Miller
Author-email: eric.miller@sprint.com
License: MIT
Keywords: communications
Platform: UNKNOWN
Classifier: Development Status :: 3 - Alpha
Classifier: Environment :: Console
Classifier: Intended Audience :: Developers
Classifier: License :: OSI Approved :: MIT License
Classifier: Operating System :: OS Independent
Classifier: Programming Language :: Python
Classifier: Topic :: Communications
Classifier: Topic :: Software Development :: Libraries :: Python Modules
